Workbook

Sheet 00_Tablero_Ejecutivo
A1: SISTEMA INTEGRAL DE INTELIGENCIA OPERACIONAL DE TRANSPORTE - MONITORA Tablero Gerencial de Control de Flota (15 Tractocamiones)
A4: INGRESOS TOTALES OPERACIÓN | D4: MARGEN OPERATIVO BRUTO | G4: COSTO PROMEDIO POR KM | J4: KILÓMETROS TOTALES RECORRIDOS | M4: PORCENTAJE KM VACÍOS
A5: ='01_Registro_Viajes'!L365 -> 2741224000 | D5: ='01_Registro_Viajes'!S365 -> 1220905180 | G5: =('01_Registro_Viajes'!N365+'01_Registro_Viajes'!O365+'01_Registro_Viajes'!P365+'01_Registro_Viajes'!Q365+'01_Registro_Viajes'!R365)/'01_Registro_Viajes'!K365 -> 5368.547 | J5: ='01_Registro_Viajes'!K365 -> 283190 | M5: ='01_Registro_Viajes'!J365/'01_Registro_Viajes'!K365 -> 0.0072742682
A7: MATRIZ DE LOS 15 INDICADORES EJECUTIVOS MONITORA
A8: N° | B8: Indicador Ejecutivo | C8: Dimensión | D8: Fórmula / Regla de Cálculo | E8: Valor Año Simulado | F8: Meta Objetivo | G8: Estado / Alerta | H8: Acción Correctiva Sugerida
A9: 1 | B9: Costo por kilómetro | C9: Rentabilidad | D9: Fórmula Estandarizada MONITORA Dim-1 | E9: =('01_Registro_Viajes'!N365+'01_Registro_Viajes'!O365+'01_Registro_Viajes'!P365+'01_Registro_Viajes'!Q365+'01_Registro_Viajes'!R365)/'01_Registro_Viajes'!K365 -> 5368.547 | F9: 6500 | G9: =IF(E9<=F9,"CONFORME","DESVIADO") -> CONFORME | H9: Monitoreo periódico y plan de acción MONITORA
A10: 2 | B10: Margen por viaje | C10: Rentabilidad | D10: Fórmula Estandarizada MONITORA Dim-2 | E10: ='01_Registro_Viajes'!S365/360 -> 3391403.3 | F10: 2100000 | G10: =IF(E10>=F10,"CONFORME","DESVIADO") -> CONFORME | H10: Monitoreo periódico y plan de acción MONITORA
A11: 3 | B11: Utilización de flota | C11: Utilización | D11: Fórmula Estandarizada MONITORA Dim-3 | E11: =AVERAGE('02_Hoja_Vida_Flota'!K5:K19) -> 0.81690039 | F11: 0.85 | G11: =IF(E11>=F11,"CONFORME","DESVIADO") -> DESVIADO | H11: Monitoreo periódico y plan de acción MONITORA
A12: 4 | B12: Horas improductivas por viaje | C12: Tiempos Muertos | D12: Fórmula Estandarizada MONITORA Dim-4 | E12: =AVERAGE('01_Registro_Viajes'!V5:V364) -> 3.4763889 | F12: 3 | G12: =IF(E12<=F12,"CONFORME","DESVIADO") -> DESVIADO | H12: Monitoreo periódico y plan de acción MONITORA
A13: 5 | B13: Disponibilidad mecánica | C13: Mantenimiento | D13: Fórmula Estandarizada MONITORA Dim-5 | E13: =AVERAGE('02_Hoja_Vida_Flota'!I5:I19) -> 0.91254827 | F13: 0.92 | G13: =IF(E13>=F13,"CONFORME","DESVIADO") -> DESVIADO | H13: Monitoreo periódico y plan de acción MONITORA
A14: 6 | B14: Mantenimiento preventivo % | C14: Mantenimiento | D14: Fórmula Estandarizada MONITORA Dim-6 | E14: =SUMIF('03_Mantenimiento'!D5:D49, "Preventivo*", '03_Mantenimiento'!H5:H49)/COUNTIF('03_Mantenimiento'!D5:D49, "Preventivo*") -> 1 | F14: 0.9 | G14: =IF(E14>=F14,"CONFORME","DESVIADO") -> CONFORME | H14: Monitoreo periódico y plan de acción MONITORA
A15: 7 | B15: Rendimiento de combustible (km/gal) | C15: Combustible | D15: Fórmula Estandarizada MONITORA Dim-7 | E15: ='01_Registro_Viajes'!K365/'01_Registro_Viajes'!M365 -> 7.2890927 | F15: 7.5 | G15: =IF(E15>=F15,"CONFORME","DESVIADO") -> DESVIADO | H15: Monitoreo periódico y plan de acción MONITORA
A16: 8 | B16: % Kilómetros vacíos | C16: Rutas | D16: Fórmula Estandarizada MONITORA Dim-8 | E16: ='01_Registro_Viajes'!J365/'01_Registro_Viajes'!K365 -> 0.0072742682 | F16: 0.05 | G16: =IF(E16<=F16,"CONFORME","DESVIADO") -> CONFORME | H16: Monitoreo periódico y plan de acción MONITORA
A17: 9 | B17: Tiempo de ciclo de viaje (horas) | C17: Rutas | D17: Fórmula Estandarizada MONITORA Dim-9 | E17: =AVERAGE('01_Registro_Viajes'!U5:U364)+AVERAGE('01_Registro_Viajes'!V5:V364)+AVERAGE('01_Registro_Viajes'!W5:W364) -> 30.960278 | F17: 26 | G17: =IF(E17<=F17,"CONFORME","DESVIADO") -> DESVIADO | H17: Monitoreo periódico y plan de acción MONITORA
A18: 10 | B18: Cumplimiento entregas a tiempo (OTD) | C18: Clientes | D18: Fórmula Estandarizada MONITORA Dim-10 | E18: =COUNTIF('01_Registro_Viajes'!Z5:Z364,"SÍ")/360 -> 0.47222222 | F18: 0.95 | G18: =IF(E18>=F18,"CONFORME","DESVIADO") -> DESVIADO | H18: Monitoreo periódico y plan de acción MONITORA
A19: 11 | B19: Incidentes viales por 100k km | C19: Seguridad | D19: Fórmula Estandarizada MONITORA Dim-11 | E19: =SUM('04_Conductores_Seguridad'!G5:G19)/('01_Registro_Viajes'!K365/100000) -> 0 | F19: 0.5 | G19: =IF(E19<=F19,"CONFORME","DESVIADO") -> CONFORME | H19: Monitoreo periódico y plan de acción MONITORA
A20: 12 | B20: Score de conducción segura (0-100) | C20: Seguridad | D20: Fórmula Estandarizada MONITORA Dim-12 | E20: =AVERAGE('04_Conductores_Seguridad'!I5:I19) -> 63.466667 | F20: 85 | G20: =IF(E20>=F20,"CONFORME","DESVIADO") -> DESVIADO | H20: Monitoreo periódico y plan de acción MONITORA
A21: 13 | B21: Cumplimiento de descansos % | C21: Conductores | D21: Fórmula Estandarizada MONITORA Dim-13 | E21: =AVERAGE('04_Conductores_Seguridad'!F5:F19) -> 0.97607975 | F21: 0.98 | G21: =IF(E21>=F21,"CONFORME","DESVIADO") -> DESVIADO | H21: Monitoreo periódico y plan de acción MONITORA
A22: 14 | B22: Costo de ciclo de vida acumulado | C22: Activos | D22: Fórmula Estandarizada MONITORA Dim-14 | E22: =SUM('02_Hoja_Vida_Flota'!N5:N19) -> 1338793180 | F22: 350000000 | G22: =IF(E22<=F22,"CONFORME","DESVIADO") -> DESVIADO | H22: Monitoreo periódico y plan de acción MONITORA
A23: 15 | B23: % Acciones correctivas cerradas | C23: Calidad/Datos | D23: Fórmula Estandarizada MONITORA Dim-15 | E23: 0.92 | F23: 0.95 | G23: =IF(E23>=F23,"CONFORME","DESVIADO") -> DESVIADO | H23: Monitoreo periódico y plan de acción MONITORA

Sheet 01_Registro_Viajes
A1: REGISTRO OPERACIONAL Y FINANCIERO DE VIAJES Y DESPACHOS (BASE DE DATOS OPERATIVA)
A4: ID Viaje | B4: Fecha Despacho | C4: Mes Operativo | D4: Placa Vehículo | E4: Conductor Asignado | F4: Cliente | G4: Ruta Origen-Destino | H4: Tipo de Carga | I4: Km Cargados | J4: Km Vacíos | K4: Km Totales | L4: Ingreso Flete (COP) | M4: Galones ACPM | N4: Costo ACPM (COP) | O4: Costo Peajes (COP) | P4: Pago Conductor (COP) | Q4: Costo Mantenimiento (COP) | R4: Otros Gastos (COP) | S4: Margen Viaje (COP) | T4: Horas Tránsito Plan | U4: Horas Tránsito Real | V4: Horas Espera Cliente/Puerto | W4: Horas Cargue/Descargue | X4: Excesos Velocidad | Y4: Frenadas Bruscas | Z4: Entrega a Tiempo (OTD)
A5: TRP-1001 | B5: 2025-01-15 | C5: 2025-01 | D5: MAD100 | E5: Carlos Mendoza | F5: Cemex Colombia | G5: Cali - Santa Marta | H5: Contenedor 40ft | I5: 1180 | J5: 0 | K5: =I5+J5 -> 1180 | L5: 10677000 | M5: 157 | N5: 2433500 | O5: 2500000 | P5: 531000 | Q5: 377600 | R5: 134886 | S5: =L5-SUM(N5:R5) -> 4700014 | T5: 28 | U5: 27.7 | V5: 2.2 | W5: 4.3 | X5: 0 | Y5: 1 | Z5: SÍ
A6: TRP-1002 | B6: 2025-01-12 | C6: 2025-01 | D6: MAD100 | E6: Carlos Mendoza | F6: Grupo Nutresa | G6: Medellín - Barranquilla | H6: Carga General Enva/Embal | I6: 700 | J6: 30 | K6: =I6+J6 -> 730 | L6: 6940000 | M6: 112.3 | N6: 1740650 | O6: 1650000 | P6: 328500 | Q6: 233600 | R6: 183355 | S6: =L6-SUM(N6:R6) -> 2803895 | T6: 18 | U6: 19.3 | V6: 2.6 | W6: 4.7 | X6: 0 | Y6: 1 | Z6: SÍ
A7: TRP-1003 | B7: 2025-01-16 | C7: 2025-01 | D7: MAD101 | E7: Jhon Jairo Gómez | F7: Cemex Colombia | G7: Buenaventura - Bogotá | H7: Carga General Enva/Embal | I7: 510 | J7: 0 | K7: =I7+J7 -> 510 | L7: 5782000 | M7: 76.6 | N7: 1187300 | O7: 1450000 | P7: 229500 | Q7: 163200 | R7: 246845 | S7: =L7-SUM(N7:R7) -> 2505155 | T7: 16 | U7: 18.5 | V7: 3.1 | W7: 3.2 | X7: 1 | Y7: 0 | Z7: NO
A8: TRP-1004 | B8: 2025-01-14 | C8: 2025-01 | D8: MAD101 | E8: Jhon Jairo Gómez | F8: Grupo Nutresa | G8: Cali - Santa Marta | H8: Carga General Enva/Embal | I8: 1180 | J8: 0 | K8: =I8+J8 -> 1180 | L8: 10339000 | M8: 168.1 | N8: 2605550 | O8: 2500000 | P8: 531000 | Q8: 377600 | R8: 148148 | S8: =L8-SUM(N8:R8) -> 4176702 | T8: 28 | U8: 29.3 | V8: 4 | W8: 5.4 | X8: 2 | Y8: 0 | Z8: SÍ
A9: TRP-1005 | B9: 2025-01-08 | C9: 2025-01 | D9: MAD102 | E9: Luis Eduardo Rodríguez | F9: Cemex Colombia | G9: Bogotá - Buenaventura | H9: Carga Granel (Granos/Minerales) | I9: 510 | J9: 0 | K9: =I9+J9 -> 510 | L9: 7039000 | M9: 70.6 | N9: 1094300 | O9: 1450000 | P9: 229500 | Q9: 163200 | R9: 158953 | S9: =L9-SUM(N9:R9) -> 3943047 | T9: 16 | U9: 15.4 | V9: 6.5 | W9: 4.8 | X9: 0 | Y9: 2 | Z9: SÍ
A10: TRP-1006 | B10: 2025-01-14 | C10: 2025-01 | D10: MAD102 | E10: Luis Eduardo Rodríguez | F10: Impala Terminals | G10: Cali - Santa Marta | H10: Carga General Enva/Embal | I10: 1180 | J10: 0 | K10: =I10+J10 -> 1180 | L10: 11305000 | M10: 179.4 | N10: 2780700 | O10: 2500000 | P10: 531000 | Q10: 377600 | R10: 135591 | S10: =L10-SUM(N10:R10) -> 4980109 | T10: 28 | U10: 35 | V10: 2.7 | W10: 5.3 | X10: 3 | Y10: 1 | Z10: NO
A11: TRP-1007 | B11: 2025-01-15 | C11: 2025-01 | D11: MAD103 | E11: Hernán Darío Patiño | F11: Ecopetrol / Cenit | G11: Medellín - Barranquilla | H11: Contenedor 40ft | I11: 700 | J11: 0 | K11: =I11+J11 -> 700 | L11: 7567000 | M11: 107.3 | N11: 1663150 | O11: 1650000 | P11: 315000 | Q11: 224000 | R11: 82568 | S11: =L11-SUM(N11:R11) -> 3632282 | T11: 18 | U11: 18.5 | V11: 0 | W11: 6.3 | X11: 1 | Y11: 1 | Z11: SÍ
A12: TRP-1008 | B12: 2025-01-10 | C12: 2025-01 | D12: MAD103 | E12: Hernán Darío Patiño | F12: Alpina Productos Alimenticios | G12: Bogotá - Buenaventura | H12: Contenedor 40ft | I12: 510 | J12: 0 | K12: =I12+J12 -> 510 | L12: 7327000 | M12: 76.2 | N12: 1181100 | O12: 1450000 | P12: 229500 | Q12: 163200 | R12: 102662 | S12: =L12-SUM(N12:R12) -> 4200538 | T12: 16 | U12: 18.1 | V12: 0.4 | W12: 4.5 | X12: 1 | Y12: 1 | Z12: SÍ
A13: TRP-1009 | B13: 2025-01-03 | C13: 2025-01 | D13: MAD104 | E13: Wilson Andrés Castro | F13: Homecenter / Sodimac | G13: Cartagena - Bogotá | H13: Carga Refrigerada | I13: 1040 | J13: 0 | K13: =I13+J13 -> 1040 | L13: 8619000 | M13: 155.1 | N13: 2404050 | O13: 2200000 | P13: 468000 | Q13: 332800 | R13: 238338 | S13: =L13-SUM(N13:R13) -> 2975812 | T13: 24 | U13: 28.2 | V13: 5.2 | W13: 5 | X13: 1 | Y13: 0 | Z13: NO
A14: TRP-1010 | B14: 2025-01-19 | C14: 2025-01 | D14: MAD104 | E14: Wilson Andrés Castro | F14: Cemex Colombia | G14: Buenaventura - Bogotá | H14: Contenedor 40ft | I14: 510 | J14: 0 | K14: =I14+J14 -> 510 | L14: 6103000 | M14: 67.3 | N14: 1043150 | O14: 1450000 | P14: 229500 | Q14: 163200 | R14: 187059 | S14: =L14-SUM(N14:R14) -> 3030091 | T14: 16 | U14: 19.7 | V14: 0.5 | W14: 5.4 | X14: 1 | Y14: 0 | Z14: NO
A15: TRP-1011 | B15: 2025-01-19 | C15: 2025-01 | D15: MAD105 | E15: José Fernando Silva | F15: Impala Terminals | G15: Medellín - Barranquilla | H15: Carga Refrigerada | I15: 700 | J15: 0 | K15: =I15+J15 -> 700 | L15: 7060000 | M15: 86.6 | N15: 1342300 | O15: 1650000 | P15: 315000 | Q15: 224000 | R15: 144044 | S15: =L15-SUM(N15:R15) -> 3384656 | T15: 18 | U15: 17.9 | V15: 2.1 | W15: 3.9 | X15: 0 | Y15: 2 | Z15: SÍ
A16: TRP-1012 | B16: 2025-01-07 | C16: 2025-01 | D16: MAD105 | E16: José Fernando Silva | F16: Grupo Nutresa | G16: Bucaramanga - Santa Marta | H16: Carga Refrigerada | I16: 540 | J16: 30 | K16: =I16+J16 -> 570 | L16: 5578000 | M16: 81.9 | N16: 1269450 | O16: 1100000 | P16: 256500 | Q16: 182400 | R16: 217848 | S16: =L16-SUM(N16:R16) -> 2551802 | T16: 12 | U16: 15.5 | V16: 0 | W16: 5 | X16: 0 | Y16: 0 | Z16: NO
... A364: TRP-1360 | B364: 2025-12-16 | C364: 2025-12 | D364: MAD114 | E364: César Augusto Hoyos | F364: Alpina Productos Alimenticios | G364: Barranquilla - Medellín | H364: Carga Refrigerada | I364: 700 | J364: 0 | K364: =I364+J364 -> 700 | L364: 6782000 | M364: 97.7 | N364: 1514350 | O364: 1650000 | P364: 315000 | Q364: 224000 | R364: 195700 | S364: =L364-SUM(N364:R364) -> 2882950 | T364: 18 | U364: 23.9 | V364: 5.3 | W364: 4.3 | X364: 0 | Y364: 1 | Z364: NO
A365: TOTALES / PROMEDIOS | I365: =SUM(I5:I364) -> 281130 | J365: =SUM(J5:J364) -> 2060 | K365: =SUM(K5:K364) -> 283190 | L365: =SUM(L5:L364) -> 2741224000 | M365: =SUM(M5:M364) -> 38851.2 | N365: =SUM(N5:N364) -> 602193600 | O365: =SUM(O5:O364) -> 639150000 | P365: =SUM(P5:P364) -> 127435500 | ... S365: =SUM(S5:S364) -> 1220905180

Sheet 02_Hoja_Vida_Flota
A1: CATÁLOGO MAESTRO Y FICHA DE INTELIGENCIA DE ACTIVO (15 TRACTOCAMIONES)
A4: Placa | B4: Marca / Línea | C4: Modelo (Año) | D4: Motor / Config | E4: Kilometraje Acumulado | F4: Conductor Habitual | G4: Estado Operativo | H4: Horas Disponibles/Año | I4: % Disponibilidad Mecánica | J4: Horas Operativas | K4: % Utilización Activo | L4: Ingresos Acumulados (COP) | M4: Mantenimientos + Reparaciones (COP) | N4: Costo Ciclo Vida Total (COP) | O4: Valor Comercial Residual Est. (COP) | P4: Decisión Gerencial Recomendada | Q4: FOTO
A5: MAD100 | B5: Kenworth T800 | C5: 2018 | D5: Cummins ISX 450hp / 6x4 | E5: 507203 | F5: Carlos Mendoza | G5: ACTIVO | H5: 8760 | I5: 0.95790403 | J5: =H5*I5*K5 -> 6887.0747 | K5: 0.82074583 | L5: =SUMIF('01_Registro_Viajes'!$D$5:$D$364, A5, '01_Registro_Viajes'!$L$5:$L$364) -> 186734000 | M5: =SUMIF('01_Registro_Viajes'!$D$5:$D$364, A5, '01_Registro_Viajes'!$Q$5:$Q$364) -> 6179200 | N5: =M5+(E5*180) -> 97475740 | O5: 170000000 | P5: PROGRAMAR REVISIÓN MAYOR / REEMPLAZO 2027 | Q5: MAD100.jpg
A6: MAD101 | B6: International ProStar | C6: 2019 | D6: Cummins ISX 450hp / 6x4 | E6: 678138 | F6: Jhon Jairo Gómez | G6: ACTIVO | H6: 8760 | I6: 0.92282944 | J6: =H6*I6*K6 -> 6657.8844 | K6: 0.82358931 | L6: =SUMIF('01_Registro_Viajes'!$D$5:$D$364, A6, '01_Registro_Viajes'!$L$5:$L$364) -> 196463000 | M6: =SUMIF('01_Registro_Viajes'!$D$5:$D$364, A6, '01_Registro_Viajes'!$Q$5:$Q$364) -> 6579200 | N6: =M6+(E6*180) -> 128644040 | O6: 205000000 | P6: PROGRAMAR REVISIÓN MAYOR / REEMPLAZO 2027 | Q6: MAD101.jpg
A7: MAD102 | B7: Freightliner Cascadia | C7: 2020 | D7: Cummins ISX 450hp / 6x4 | E7: 574150 | F7: Luis Eduardo Rodríguez | G7: ACTIVO | H7: 8760 | I7: 0.89055723 | J7: =H7*I7*K7 -> 6371.4141 | K7: 0.8167138 | L7: =SUMIF('01_Registro_Viajes'!$D$5:$D$364, A7, '01_Registro_Viajes'!$L$5:$L$364) -> 188716000 | M7: =SUMIF('01_Registro_Viajes'!$D$5:$D$364, A7, '01_Registro_Viajes'!$Q$5:$Q$364) -> 6352000 | N7: =M7+(E7*180) -> 109699000 | O7: 240000000 | P7: MANTENER EN OPERACIÓN | Q7: MAD102.jpg
A8: MAD103 | B8: Volvo FH | C8: 2021 | D8: Cummins ISX 450hp / 6x4 | E8: 434599 | F8: Hernán Darío Patiño | G8: ACTIVO | H8: 8760 | I8: 0.88745569 | J8: =H8*I8*K8 -> 6245.4451 | K8: 0.80336445 | L8: =SUMIF('01_Registro_Viajes'!$D$5:$D$364, A8, '01_Registro_Viajes'!$L$5:$L$364) -> 196641000 | M8: =SUMIF('01_Registro_Viajes'!$D$5:$D$364, A8, '01_Registro_Viajes'!$Q$5:$Q$364) -> 6441600 | N8: =M8+(E8*180) -> 84669420 | O8: 275000000 | P8: MANTENER EN OPERACIÓN | Q8: MAD103.jpg
A9: MAD104 | B9: Scania R450 | C9: 2022 | D9: Cummins ISX 450hp / 6x4 | E9: 308202 | F9: Wilson Andrés Castro | G9: ACTIVO | H9: 8760 | I9: 0.9444519 | J9: =H9*I9*K9 -> 6446.313 | K9: 0.77916141 | L9: =SUMIF('01_Registro_Viajes'!$D$5:$D$364, A9, '01_Registro_Viajes'!$L$5:$L$364) -> 182848000 | M9: =SUMIF('01_Registro_Viajes'!$D$5:$D$364, A9, '01_Registro_Viajes'!$Q$5:$Q$364) -> 6070400 | N9: =M9+(E9*180) -> 61546760 | O9: 310000000 | P9: MANTENER EN OPERACIÓN | Q9: MAD104.jpg
A10: MAD105 | B10: Kenworth T800 | C10: 2018 | D10: Cummins ISX 450hp / 6x4 | E10: 300855 | F10: José Fernando Silva | G10: ACTIVO | H10: 8760 | I10: 0.90075107 | J10: =H10*I10*K10 -> 6007.7835 | K10: 0.76138687 | L10: =SUMIF('01_Registro_Viajes'!$D$5:$D$364, A10, '01_Registro_Viajes'!$L$5:$L$364) -> 178489000 | M10: =SUMIF('01_Registro_Viajes'!$D$5:$D$364, A10, '01_Registro_Viajes'!$Q$5:$Q$364) -> 5942400 | N10: =M10+(E10*180) -> 60096300 | O10: 170000000 | P10: PROGRAMAR REVISIÓN MAYOR / REEMPLAZO 2027 | Q10: MAD105.jpg
A11: MAD106 | B11: International ProStar | C11: 2019 | D11: Cummins ISX 450hp / 6x4 | E11: 591385 | F11: Oscar Mario Ramírez | G11: ACTIVO | H11: 8760 | I11: 0.88762887 | J11: =H11*I11*K11 -> 6286.6553 | K11: 0.80850762 | L11: =SUMIF('01_Registro_Viajes'!$D$5:$D$364, A11, '01_Registro_Viajes'!$L$5:$L$364) -> 180025000 | M11: =SUMIF('01_Registro_Viajes'!$D$5:$D$364, A11, '01_Registro_Viajes'!$Q$5:$Q$364) -> 6000000 | N11: =M11+(E11*180) -> 112449300 | O11: 205000000 | P11: PROGRAMAR REVISIÓN MAYOR / REEMPLAZO 2027 | Q11: MAD106.jpg
A12: MAD107 | B12: Freightliner Cascadia | C12: 2020 | D12: Cummins ISX 450hp / 6x4 | E12: 503068 | F12: Diego Alejandro Torres | G12: ACTIVO | H12: 8760 | I12: 0.93011656 | J12: =H12*I12*K12 -> 6415.2071 | K12: 0.78735247 | L12: =SUMIF('01_Registro_Viajes'!$D$5:$D$364, A12, '01_Registro_Viajes'!$L$5:$L$364) -> 171236000 | M12: =SUMIF('01_Registro_Viajes'!$D$5:$D$364, A12, '01_Registro_Viajes'!$Q$5:$Q$364) -> 5619200 | N12: =M12+(E12*180) -> 96171440 | O12: 240000000 | P12: MANTENER EN OPERACIÓN | Q12: MAD107.jpg
A13: MAD108 | B13: Volvo FH | C13: 2021 | D13: Cummins ISX 450hp / 6x4 | E13: 635990 | F13: Jorge Eliecer Morales | G13: ACTIVO | H13: 8760 | I13: 0.89689008 | J13: =H13*I13*K13 -> 6661.1227 | K13: 0.84782088 | L13: =SUMIF('01_Registro_Viajes'!$D$5:$D$364, A13, '01_Registro_Viajes'!$L$5:$L$364) -> 178094000 | M13: =SUMIF('01_Registro_Viajes'!$D$5:$D$364, A13, '01_Registro_Viajes'!$Q$5:$Q$364) -> 5651200 | N13: =M13+(E13*180) -> 120129400 | O13: 275000000 | P13: MANTENER EN OPERACIÓN | Q13: MAD108.jpg
A14: MAD109 | B14: Scania R450 | C14: 2022 | D14: Cummins ISX 450hp / 6x4 | E14: 384428 | F14: Felipe Antonio Ruiz | G14: ACTIVO | H14: 8760 | I14: 0.94965071 | J14: =H14*I14*K14 -> 7060.129 | K14: 0.8486813 | L14: =SUMIF('01_Registro_Viajes'!$D$5:$D$364, A14, '01_Registro_Viajes'!$L$5:$L$364) -> 178864000 | M14: =SUMIF('01_Registro_Viajes'!$D$5:$D$364, A14, '01_Registro_Viajes'!$Q$5:$Q$364) -> 5952000 | N14: =M14+(E14*180) -> 75149040 | O14: 310000000 | P14: MANTENER EN OPERACIÓN | Q14: MAD109.jpg
A15: MAD110 | B15: Kenworth T800 | C15: 2018 | D15: Cummins ISX 450hp / 6x4 | E15: 497282 | F15: Gabriel Omar Vargas | G15: ACTIVO | H15: 8760 | I15: 0.91875129 | J15: =H15*I15*K15 -> 6762.1067 | K15: 0.84019472 | L15: =SUMIF('01_Registro_Viajes'!$D$5:$D$364, A15, '01_Registro_Viajes'!$L$5:$L$364) -> 189810000 | M15: =SUMIF('01_Registro_Viajes'!$D$5:$D$364, A15, '01_Registro_Viajes'!$Q$5:$Q$364) -> 6470400 | N15: =M15+(E15*180) -> 95981160 | O15: 170000000 | P15: PROGRAMAR REVISIÓN MAYOR / REEMPLAZO 2027 | Q15: MAD110.jpg
A16: MAD111 | B16: International ProStar | C16: 2019 | D16: Cummins ISX 450hp / 6x4 | E16: 400243 | F16: Jaime Alberto Ospina | G16: ACTIVO | H16: 8760 | I16: 0.89290939 | J16: =H16*I16*K16 -> 6448.046 | K16: 0.82435946 | L16: =SUMIF('01_Registro_Viajes'!$D$5:$D$364, A16, '01_Registro_Viajes'!$L$5:$L$364) -> 178085000 | M16: =SUMIF('01_Registro_Viajes'!$D$5:$D$364, A16, '01_Registro_Viajes'!$Q$5:$Q$364) -> 5792000 | N16: =M16+(E16*180) -> 77835740 | O16: 205000000 | P16: PROGRAMAR REVISIÓN MAYOR / REEMPLAZO 2027 | Q16: MAD111.jpg
... A19: MAD114 | B19: Scania R450 | C19: 2022 | D19: Cummins ISX 450hp / 6x4 | E19: 283969 | F19: César Augusto Hoyos | G19: ACTIVO | H19: 8760 | I19: 0.91267645 | J19: =H19*I19*K19 -> 6702.7316 | K19: 0.83836064 | L19: =SUMIF('01_Registro_Viajes'!$D$5:$D$364, A19, '01_Registro_Viajes'!$L$5:$L$364) -> 178132000 | M19: =SUMIF('01_Registro_Viajes'!$D$5:$D$364, A19, '01_Registro_Viajes'!$Q$5:$Q$364) -> 5785600 | N19: =M19+(E19*180) -> 56900020 | O19: 310000000 | P19: MANTENER EN OPERACIÓN | Q19: MAD114.jpg

Sheet 03_Mantenimiento
A1: CONTROL DE MANTENIMIENTO PREVENTIVO, CORRECTIVO Y DISPONIBILIDAD MECÁNICA
A4: ID OT | B4: Placa | C4: Fecha Mantenimiento | D4: Tipo Mantenimiento | E4: Descripción de la Intervención / Falla | F4: Proveedor / Taller | G4: Costo Total (COP) | H4: Cumplimiento Preventivo A Tiempo | I4: Horas Inmovilizado | J4: Kilometraje en Intervención | K4: Estado OT
A5: OT-101 | B5: MAD104 | C5: 2025-07-02 | D5: Correctivo Suspensión | E5: Rutina de mantenimiento Correctivo Suspensión según manual de fabricante | F5: Taller Central Bogotá | G5: 7021452 | H5: 0 | I5: 42 | J5: 557450 | K5: CERRADA
A6: OT-102 | B6: MAD113 | C6: 2025-04-20 | D6: Correctivo Sistema Inyección | E6: Rutina de mantenimiento Correctivo Sistema Inyección según manual de fabricante | F6: Navitrans Cali | G6: 6085315 | H6: 0 | I6: 45 | J6: 497539 | K6: CERRADA
A7: OT-103 | B7: MAD108 | C7: 2025-06-20 | D7: Preventivo 10k | E7: Rutina de mantenimiento Preventivo 10k según manual de fabricante | F7: Navitrans Cali | G7: 5729426 | H7: 1 | I7: 9 | J7: 363928 | K7: CERRADA
A8: OT-104 | B8: MAD103 | C8: 2025-05-20 | D8: Correctivo Frenos | E8: Rutina de mantenimiento Correctivo Frenos según manual de fabricante | F8: Navitrans Cali | G8: 2065635 | H8: 0 | I8: 41 | J8: 454237 | K8: CERRADA
A9: OT-105 | B9: MAD110 | C9: 2025-02-13 | D9: Preventivo 30k | E9: Rutina de mantenimiento Preventivo 30k según manual de fabricante | F9: Kenworth de la Montaña | G9: 5578972 | H9: 1 | I9: 15 | J9: 375910 | K9: CERRADA
A10: OT-106 | B10: MAD103 | C10: 2025-03-25 | D10: Correctivo Sistema Inyección | E10: Rutina de mantenimiento Correctivo Sistema Inyección según manual de fabricante | F10: Taller Central Bogotá | G10: 5147965 | H10: 0 | I10: 54 | J10: 354460 | K10: CERRADA
A11: OT-107 | B11: MAD114 | C11: 2025-11-20 | D11: Preventivo 10k | E11: Rutina de mantenimiento Preventivo 10k según manual de fabricante | F11: Kenworth de la Montaña | G11: 4598196 | H11: 1 | I11: 5 | J11: 398064 | K11: CERRADA
A12: OT-108 | B12: MAD113 | C12: 2025-07-21 | D12: Preventivo 10k | E12: Rutina de mantenimiento Preventivo 10k según manual de fabricante | F12: Diesel del Caribe | G12: 5127552 | H12: 1 | I12: 14 | J12: 483622 | K12: CERRADA
A13: OT-109 | B13: MAD109 | C13: 2025-01-11 | D13: Preventivo 30k | E13: Rutina de mantenimiento Preventivo 30k según manual de fabricante | F13: Diesel del Caribe | G13: 5422942 | H13: 1 | I13: 4 | J13: 569279 | K13: CERRADA
A14: OT-110 | B14: MAD100 | C14: 2025-10-24 | D14: Correctivo Frenos | E14: Rutina de mantenimiento Correctivo Frenos según manual de fabricante | F14: Diesel del Caribe | G14: 11812390 | H14: 0 | I14: 25 | J14: 555083 | K14: CERRADA
A15: OT-111 | B15: MAD102 | C15: 2025-11-11 | D15: Preventivo 10k | E15: Rutina de mantenimiento Preventivo 10k según manual de fabricante | F15: Taller Central Bogotá | G15: 3531303 | H15: 1 | I15: 5 | J15: 480418 | K15: CERRADA
A16: OT-112 | B16: MAD109 | C16: 2025-02-22 | D16: Cambio Llantas Eje Motriz | E16: Rutina de mantenimiento Cambio Llantas Eje Motriz según manual de fabricante | F16: Kenworth de la Montaña | G16: 8318753 | H16: 0 | I16: 39 | J16: 510515 | K16: CERRADA
... A49: OT-145 | B49: MAD113 | C49: 2025-03-16 | D49: Preventivo 10k | E49: Rutina de mantenimiento Preventivo 10k según manual de fabricante | F49: Kenworth de la Montaña | G49: 6194779 | H49: 1 | I49: 4 | J49: 335315 | K49: CERRADA

Sheet 04_Conductores_Seguridad
A1: MATRIZ DE CONDUCTORES, SEGURIDAD VIAL (PESV) Y TELEMÁTICA DE CONDUCCIÓN
A4: Nombre Conductor | B4: Placa Asignada | C4: Cédula / ID | D4: Certificación PESV | E4: Capacitación Vigente | F4: % Cumplimiento Descansos | G4: Incidentes Viales Año | H4: Excesos Velocidad Totales | I4: Score Conducción Segura (0-100) | J4: Nivel de Riesgo
A5: Carlos Mendoza | B5: MAD100 | C5: CC-79000000 | D5: VIGENTE | E5: SÍ | F5: 0.97003521 | G5: 0 | H5: =SUMIF('01_Registro_Viajes'!$E$5:$E$364, A5, '01_Registro_Viajes'!$X$5:$X$364) -> 16 | I5: =MAX(60, 100 - (H5*2) - (G5*10)) -> 68 | J5: =IF(I5>=85, "BAJO", IF(I5>=70, "MEDIO", "ALTO")) -> ALTO
A6: Jhon Jairo Gómez | B6: MAD101 | C6: CC-79001500 | D6: VIGENTE | E6: SÍ | F6: 0.99416368 | G6: 0 | H6: =SUMIF('01_Registro_Viajes'!$E$5:$E$364, A6, '01_Registro_Viajes'!$X$5:$X$364) -> 28 | I6: =MAX(60, 100 - (H6*2) - (G6*10)) -> 60 | J6: =IF(I6>=85, "BAJO", IF(I6>=70, "MEDIO", "ALTO")) -> ALTO
A7: Luis Eduardo Rodríguez | B7: MAD102 | C7: CC-79003000 | D7: VIGENTE | E7: SÍ | F7: 0.96936372 | G7: 0 | H7: =SUMIF('01_Registro_Viajes'!$E$5:$E$364, A7, '01_Registro_Viajes'!$X$5:$X$364) -> 23 | I7: =MAX(60, 100 - (H7*2) - (G7*10)) -> 60 | J7: =IF(I7>=85, "BAJO", IF(I7>=70, "MEDIO", "ALTO")) -> ALTO
A8: Hernán Darío Patiño | B8: MAD103 | C8: CC-79004500 | D8: VIGENTE | E8: SÍ | F8: 0.97210167 | G8: 0 | H8: =SUMIF('01_Registro_Viajes'!$E$5:$E$364, A8, '01_Registro_Viajes'!$X$5:$X$364) -> 11 | I8: =MAX(60, 100 - (H8*2) - (G8*10)) -> 78 | J8: =IF(I8>=85, "BAJO", IF(I8>=70, "MEDIO", "ALTO")) -> MEDIO
A9: Wilson Andrés Castro | B9: MAD104 | C9: CC-79006000 | D9: VIGENTE | E9: SÍ | F9: 0.95307231 | G9: 0 | H9: =SUMIF('01_Registro_Viajes'!$E$5:$E$364, A9, '01_Registro_Viajes'!$X$5:$X$364) -> 22 | I9: =MAX(60, 100 - (H9*2) - (G9*10)) -> 60 | J9: =IF(I9>=85, "BAJO", IF(I9>=70, "MEDIO", "ALTO")) -> ALTO
A10: José Fernando Silva | B10: MAD105 | C10: CC-79007500 | D10: VIGENTE | E10: SÍ | F10: 0.9970252 | G10: 0 | H10: =SUMIF('01_Registro_Viajes'!$E$5:$E$364, A10, '01_Registro_Viajes'!$X$5:$X$364) -> 11 | I10: =MAX(60, 100 - (H10*2) - (G10*10)) -> 78 | J10: =IF(I10>=85, "BAJO", IF(I10>=70, "MEDIO", "ALTO")) -> MEDIO
A11: Oscar Mario Ramírez | B11: MAD106 | C11: CC-79009000 | D11: VIGENTE | E11: SÍ | F11: 0.9977283 | G11: 0 | H11: =SUMIF('01_Registro_Viajes'!$E$5:$E$364, A11, '01_Registro_Viajes'!$X$5:$X$364) -> 20 | I11: =MAX(60, 100 - (H11*2) - (G11*10)) -> 60 | J11: =IF(I11>=85, "BAJO", IF(I11>=70, "MEDIO", "ALTO")) -> ALTO
A12: Diego Alejandro Torres | B12: MAD107 | C12: CC-79010500 | D12: VIGENTE | E12: SÍ | F12: 0.97387081 | G12: 0 | H12: =SUMIF('01_Registro_Viajes'!$E$5:$E$364, A12, '01_Registro_Viajes'!$X$5:$X$364) -> 19 | I12: =MAX(60, 100 - (H12*2) - (G12*10)) -> 62 | J12: =IF(I12>=85, "BAJO", IF(I12>=70, "MEDIO", "ALTO")) -> ALTO
A13: Jorge Eliecer Morales | B13: MAD108 | C13: CC-79012000 | D13: VIGENTE | E13: SÍ | F13: 0.97908683 | G13: 0 | H13: =SUMIF('01_Registro_Viajes'!$E$5:$E$364, A13, '01_Registro_Viajes'!$X$5:$X$364) -> 17 | I13: =MAX(60, 100 - (H13*2) - (G13*10)) -> 66 | J13: =IF(I13>=85, "BAJO", IF(I13>=70, "MEDIO", "ALTO")) -> ALTO
A14: Felipe Antonio Ruiz | B14: MAD109 | C14: CC-79013500 | D14: VIGENTE | E14: SÍ | F14: 0.96690422 | G14: 0 | H14: =SUMIF('01_Registro_Viajes'!$E$5:$E$364, A14, '01_Registro_Viajes'!$X$5:$X$364) -> 25 | I14: =MAX(60, 100 - (H14*2) - (G14*10)) -> 60 | J14: =IF(I14>=85, "BAJO", IF(I14>=70, "MEDIO", "ALTO")) -> ALTO
A15: Gabriel Omar Vargas | B15: MAD110 | C15: CC-79015000 | D15: VIGENTE | E15: SÍ | F15: 0.96958712 | G15: 0 | H15: =SUMIF('01_Registro_Viajes'!$E$5:$E$364, A15, '01_Registro_Viajes'!$X$5:$X$364) -> 23 | I15: =MAX(60, 100 - (H15*2) - (G15*10)) -> 60 | J15: =IF(I15>=85, "BAJO", IF(I15>=70, "MEDIO", "ALTO")) -> ALTO
A16: Jaime Alberto Ospina | B16: MAD111 | C16: CC-79016500 | D16: VIGENTE | E16: SÍ | F16: 0.98671828 | G16: 0 | H16: =SUMIF('01_Registro_Viajes'!$E$5:$E$364, A16, '01_Registro_Viajes'!$X$5:$X$364) -> 31 | I16: =MAX(60, 100 - (H16*2) - (G16*10)) -> 60 | J16: =IF(I16>=85, "BAJO", IF(I16>=70, "MEDIO", "ALTO")) -> ALTO
... A19: César Augusto Hoyos | B19: MAD114 | C19: CC-79021000 | D19: VIGENTE | E19: SÍ | F19: 0.97884908 | G19: 0 | H19: =SUMIF('01_Registro_Viajes'!$E$5:$E$364, A19, '01_Registro_Viajes'!$X$5:$X$364) -> 20 | I19: =MAX(60, 100 - (H19*2) - (G19*10)) -> 60 | J19: =IF(I19>=85, "BAJO", IF(I19>=70, "MEDIO", "ALTO")) -> ALTO

Sheet 05_Diccionario_Indicadores
A1: CATÁLOGO MAESTRO Y DICCIONARIO DE INDICADORES - METODOLOGÍA MONITORA
A4: Dimensión | B4: Nombre del Indicador | C4: Fórmula / Regla de Cálculo | D4: Fuente de Datos | E4: Periodicidad | F4: Meta / Estándar | G4: Responsable del Control
A5: Rentabilidad y costos | B5: Costo total por km | C5: Costos operativos del periodo / km recorridos | D5: Contabilidad / Registro Viajes | E5: Mensual | F5: < $6.500 COP/km | G5: Gerente Financiero
A6: Rentabilidad y costos | B6: Margen por viaje | C6: Ingresos del viaje - costos atribuibles | D6: Registro Viajes | E6: Por viaje | F6: > 20% sobre Flete | G6: Director Operativo
A7: Rutas y productividad | B7: Cumplimiento OTD | C7: Entregas en ventana / Entregas totales | D7: GPS / Manifiestos | E7: Semanal | F7: > 95% | G7: Jefe de Despachos
A8: Rutas y productividad | B8: Kilómetros vacíos % | C8: Km sin carga / Km totales | D8: Telemetría / GPS | E8: Mensual | F8: < 5.0% | G8: Coordinador de Logística
A9: Mantenimiento | B9: Disponibilidad mecánica | C9: Horas disponibles para operar / Horas programadas | D9: Órdenes de Trabajo Taller | E9: Mensual | F9: > 92% | G9: Jefe de Mantenimiento
A10: Mantenimiento | B10: Cumplimiento preventivo | C10: Mantenimientos preventivos a tiempo / Programados | D10: Plan Mantenimiento Taller | E10: Mensual | F10: > 90% | G10: Jefe de Mantenimiento
A11: Conductores y PESV | B11: Excesos de velocidad | C11: Eventos validados por encima del límite | D11: GPS / Telemetría | E11: Semanal | F11: 0 eventos críticos | G11: Coordinador PESV / HSE
A12: Conductores y PESV | B12: Score de conducción | C12: Puntuación ponderada de telemetría | D12: Sistema Telemático | E12: Mensual | F12: > 85 / 100 | G12: Coordinador PESV
A13: Tiempos muertos | B13: Tiempo de espera en puerto/patio | C13: Hora inicio servicio - Hora arrival registrada | D13: Registros de Puertos / GPS | E13: Por viaje | F13: < 3.0 Horas | G13: Director Operativo
A14: Combustible | B14: Rendimiento de combustible | C14: Km recorridos / Galones consumidos | D14: Control de Abastecimiento | E14: Mensual | F14: > 7.5 Km/Gal | G14: Jefe de Flota
